umlsequence2/__init__.py
umlsequence2/config.py
umlsequence2/converter.py
umlsequence2/main.py
umlsequence2/parser.py
umlsequence2/svg_renderer.py
umlsequence2/uml_builder.py
umlsequence2-2.0.5.dist-info/LICENSE
umlsequence2-2.0.5.dist-info/METADATA
umlsequence2-2.0.5.dist-info/WHEEL
umlsequence2-2.0.5.dist-info/entry_points.txt
umlsequence2-2.0.5.dist-info/top_level.txt
umlsequence2-2.0.5.dist-info/RECORD
