Metadata-Version: 2.1
Name: umlsequence2
Version: 2.0.5
Summary: UML Sequence diagram generator from text input
Home-page: https://github.com/pbauermeister/umlsequence2
Author: Pascal Bauermeister
Author-email: pascal.bauermeister@gmail.com
License: GNU General Public License v3 (GPLv3)
Project-URL: Bug Tracker, https://github.com/pbauermeister/umlsequence2/issues
Classifier: Programming Language :: Python :: 3
Classifier: License :: OSI Approved :: GNU General Public License v3 (GPLv3)
Classifier: Operating System :: OS Independent
Requires-Python: >=3.6
License-File: LICENSE
Requires-Dist: svgwrite
Requires-Dist: svglib
Requires-Dist: reportlab
